thonny_seal/__init__.py
thonny_seal/__main__.py
thonny_seal/main.py
thonny_seal/py.typed
thonny_sealed-1.0.0b2.data/data/LICENSE
thonny_sealed-1.0.0b2.data/data/README.rst
thonny_sealed-1.0.0b2.data/data/requirements.txt
thonnycontrib/thonny_sealed/__init__.py
thonnycontrib/thonny_sealed/py.typed
thonny_sealed-1.0.0b2.dist-info/LICENSE
thonny_sealed-1.0.0b2.dist-info/METADATA
thonny_sealed-1.0.0b2.dist-info/WHEEL
thonny_sealed-1.0.0b2.dist-info/entry_points.txt
thonny_sealed-1.0.0b2.dist-info/top_level.txt
thonny_sealed-1.0.0b2.dist-info/RECORD
