Metadata-Version: 2.1
Name: thonny-sealed
Version: 1.0.0b2
Summary: Restrict writing to certain areas in the Thonny editor based on code comments.
Home-page: https://github.com/mristin/thonny-sealed
Author: Marko Ristin
Author-email: marko@ristin.ch
License: License :: OSI Approved :: MIT License
Keywords: restrict writing problem solution exercise area
Platform: UNKNOWN
Classifier: Development Status :: 5 - Production/Stable
Classifier: Environment :: MacOS X
Classifier: Environment :: Win32 (MS Windows)
Classifier: Environment :: X11 Applications
Classifier: Intended Audience :: Developers
Classifier: Intended Audience :: Education
Classifier: Intended Audience :: End Users/Desktop
Classifier: License :: Freeware
Classifier: License :: OSI Approved :: MIT License
Classifier: Natural Language :: English
Classifier: Operating System :: MacOS
Classifier: Operating System :: Microsoft :: Windows
Classifier: Operating System :: POSIX
Classifier: Operating System :: POSIX :: Linux
Classifier: Programming Language :: Python
Classifier: Programming Language :: Python :: 3
Classifier: Programming Language :: Python :: 3 :: Only
Classifier: Programming Language :: Python :: 3.7
Classifier: Programming Language :: Python :: 3.8
Classifier: Topic :: Education
Classifier: Topic :: Software Development
Requires-Python: >=3.7
Requires-Dist: thonny (<4,>=3.0.0)
Requires-Dist: icontract (>=2.5.1)
Provides-Extra: dev
Requires-Dist: black (==20.8b1) ; extra == 'dev'
Requires-Dist: mypy (==0.812) ; extra == 'dev'
Requires-Dist: pylint (==2.3.1) ; extra == 'dev'
Requires-Dist: pydocstyle (<3,>=2.1.1) ; extra == 'dev'
Requires-Dist: coverage (<5,>=4.5.1) ; extra == 'dev'
Requires-Dist: docutils (<1,>=0.14) ; extra == 'dev'
Requires-Dist: icontract (>=2.5.0) ; extra == 'dev'
Requires-Dist: prettytable (<3,>=2.1.0) ; extra == 'dev'
Requires-Dist: icontract-hypothesis (<2,>=1.1.2) ; extra == 'dev'
Requires-Dist: twine ; extra == 'dev'
